.hgignore
.hgtags
CHANGES.txt
README.txt
setup.py
fsd/__init__.py
fsd.core.egg-info/PKG-INFO
fsd.core.egg-info/SOURCES.txt
fsd.core.egg-info/dependency_links.txt
fsd.core.egg-info/entry_points.txt
fsd.core.egg-info/not-zip-safe
fsd.core.egg-info/requires.txt
fsd.core.egg-info/top_level.txt
fsd/core/__init__.py
fsd/core/base.py
fsd/core/configuration.py
fsd/core/configure.zcml
fsd/core/groupdata.py
fsd/core/meta.zcml
fsd/core/permissions.zcml
fsd/core/person.py
fsd/core/persongrouping.py
fsd/core/sources.py
fsd/core/testing.py
fsd/core/groupdata_templates/inline.pt
fsd/core/persongrouping_templates/people.pt
fsd/core/persongrouping_templates/view.pt
fsd/core/profiles/default/catalog.xml
fsd/core/profiles/default/metadata.xml
fsd/core/profiles/default/types.xml
fsd/core/profiles/default/types/fsd.core.groupdata.xml
fsd/core/profiles/default/types/fsd.core.person.xml
fsd/core/profiles/default/types/fsd.core.persongrouping.xml
fsd/core/static/person.png
fsd/core/static/persongrouping.png
fsd/core/tests/__init__.py
fsd/core/tests/base.py
fsd/core/tests/testGroupData.py
fsd/core/tests/testInstall.py
fsd/core/tests/testPerson.py
fsd/core/tests/testPersonGrouping.py
fsd/core/tests/test_sources.py
fsd/core/widgets/__init__.py
fsd/core/widgets/configure.zcml
fsd/core/widgets/grouping.py
fsd/core/widgets/grouping_display.pt
fsd/core/widgets/grouping_input.pt