Metadata-Version: 1.0
Name: fsd.core
Version: 1.0a1
Summary: UNKNOWN
Home-page: UNKNOWN
Author: WebLion Group, Penn State University
Author-email: support@weblion.psu.edu
License: GPL
Keywords: weblion
Platform: UNKNOWN
Classifier: Framework :: Plone
Classifier: Programming Language :: Python
Classifier: Intended Audience :: Developers
Classifier: Development Status :: 3 - Alpha
